seamless/__init__.py
seamless/websocketserver.py
seamless/core/__init__.py
seamless/core/cache_signature.py
seamless/core/cached_compile.py
seamless/core/cell.py
seamless/core/connection_finder.py
seamless/core/context.py
seamless/core/fromfile.py
seamless/core/fromfile_caching.py
seamless/core/fromfile_manager.py
seamless/core/libmanager.py
seamless/core/macro.py
seamless/core/macro_object.py
seamless/core/manager.py
seamless/core/observer.py
seamless/core/reactor.py
seamless/core/registrar.py
seamless/core/resource.py
seamless/core/tofile.py
seamless/core/tofile_manager.py
seamless/core/transformer.py
seamless/core/utils.py
seamless/core/worker.py
seamless/core/pysynckernel/__init__.py
seamless/core/pysynckernel/reactor.py
seamless/core/pysynckernel/reactor_pins.py
seamless/core/pythreadkernel/__init__.py
seamless/core/pythreadkernel/killable_thread.py
seamless/core/pythreadkernel/transformer.py
seamless/dtypes/__init__.py
seamless/dtypes/cson.py
seamless/dtypes/objects.py
seamless/dtypes/gl/GLStore.py
seamless/dtypes/gl/__init__.py
seamless/dtypes/gl/color/__init__.py
seamless/dtypes/gl/color/_color_dict.py
seamless/dtypes/gl/color/color_array.py
seamless/dtypes/gl/color/color_space.py
seamless/dtypes/gl/gloo/__init__.py
seamless/dtypes/gl/gloo/glir.py
seamless/dtypes/gl/gloo/texture.py
seamless/gui/__init__.py
seamless/gui/shell.py
seamless/lib/__init__.py
seamless/lib/cell-dynamic-html-start.py
seamless/lib/cell-filehash-start.py
seamless/lib/cell-filelink-start.py
seamless/lib/cell-itransformer.py
seamless/lib/cell-templateer.py
seamless/lib/cell-timer.py
seamless/lib/dynamic_html.py
seamless/lib/filehash.py
seamless/lib/filelink.py
seamless/lib/init.py
seamless/lib/itransformer.py
seamless/lib/templateer.py
seamless/lib/timer.py
seamless/lib/gui/__init__.py
seamless/lib/gui/basic_display.py
seamless/lib/gui/basic_editor.py
seamless/lib/gui/browser.py
seamless/lib/gui/cell-basic_display_UPDATE.py
seamless_framework-0.1.5.dist-info/DESCRIPTION.rst
seamless_framework-0.1.5.dist-info/METADATA
seamless_framework-0.1.5.dist-info/RECORD
seamless_framework-0.1.5.dist-info/WHEEL
seamless_framework-0.1.5.dist-info/entry_points.txt
seamless_framework-0.1.5.dist-info/metadata.json
seamless_framework-0.1.5.dist-info/top_level.txt
