Metadata-Version: 2.0
Name: seamless-framework
Version: 0.1.5
Summary: a cell-based reactive programming framework
Home-page: https://github.com/sjdv1982/seamless
Author: Sjoerd de Vries
Author-email: sjdv1982@gmail.com
License: MIT
Keywords: live reactive interactive programming visualization
Platform: UNKNOWN
Classifier: Development Status :: 3 - Alpha
Classifier: Intended Audience :: Developers
Classifier: Intended Audience :: Science/Research
Classifier: Topic :: Scientific/Engineering :: Visualization
Classifier: Topic :: Software Development
Classifier: Topic :: Software Development :: Object Brokering
Classifier: Topic :: Software Development :: User Interfaces
Classifier: Topic :: System
Classifier: Framework :: IPython
Classifier: License :: OSI Approved :: MIT License
Classifier: Programming Language :: Python :: 3
Classifier: Programming Language :: Python :: 3.5
Classifier: Programming Language :: Python :: 3.6
Requires-Python: >=3.5
Requires-Dist: PyOpenGL
Requires-Dist: cson
Requires-Dist: ipython
Requires-Dist: lxml
Requires-Dist: numpy
Requires-Dist: pyqt5
Requires-Dist: qtconsole
Provides-Extra: recommended
Requires-Dist: cython; extra == 'recommended'
Requires-Dist: pandas; extra == 'recommended'
Requires-Dist: scipy; extra == 'recommended'
Requires-Dist: websockets; extra == 'recommended'
